scrapy_redis_httpcache/__init__.py
scrapy_redis_httpcache/httpcache.py
scrapy_redis_httpcache-1.4.0.dist-info/METADATA
scrapy_redis_httpcache-1.4.0.dist-info/WHEEL
scrapy_redis_httpcache-1.4.0.dist-info/licenses/LICENSE
scrapy_redis_httpcache-1.4.0.dist-info/RECORD
