Metadata-Version: 2.4
Name: scrapy-redis-httpcache
Version: 1.4.0
Summary: Cache Scrapy responses with Redis.
Project-URL: Homepage, https://github.com/stefanofusai/scrapy-redis-httpcache
Project-URL: Repository, https://github.com/stefanofusai/scrapy-redis-httpcache
Author-email: Stefano Fusai <stefanofusai@gmail.com>
Maintainer-email: Stefano Fusai <stefanofusai@gmail.com>
License-File: LICENSE
Requires-Python: >=3.12
Requires-Dist: redis<6.0.0,>=5.0.0
Requires-Dist: scrapy<3.0.0,>=2.10.0
